{
  "generated_at": "2026-07-18T20:01:34.822052+00:00",
  "window_hours": 48,
  "items": [
    {
      "story_id": "s_84698b120dc47d16",
      "title": "AI",
      "canonical_url": "https://cockroachlabs.com/blog/ai",
      "first_seen": "2026-07-18T03:36:11.080822+00:00",
      "surface_count": 9,
      "surfaces": [
        {
          "url": "https://cockroachlabs.com/blog/ai",
          "name": "Cockroach Labs Blog",
          "points": null,
          "comments": null
        },
        {
          "url": "https://colobu.com/2026/07/04/ai-skill-sniffs-out-code-smells/",
          "name": "Colobu (Daniel Qian)",
          "points": null,
          "comments": null
        },
        {
          "url": "https://nlathia.github.io/2024/12/In-AI.html",
          "name": "Neal Lathia (nlathia.github.io)",
          "points": null,
          "comments": null
        },
        {
          "url": "https://blog.vonng.com/ai/mind-price/",
          "name": "Vonng's Blog (Feng Ruohang)",
          "points": null,
          "comments": null
        },
        {
          "url": "https://www.safeai.news/p/ai",
          "name": "AI Safety & Governance Newsletter (Victor Akinwande)",
          "points": null,
          "comments": null
        }
      ],
      "velocity_hours": 0.3,
      "points": 0,
      "comments": 0,
      "score": 15.0,
      "curated": false,
      "pick_id": null
    },
    {
      "story_id": "s_0fd1aab3b10380c5",
      "title": "Regressive JPEGs",
      "canonical_url": "https://maurycyz.com/projects/bad_jpeg",
      "first_seen": "2026-07-18T04:31:13+00:00",
      "surface_count": 5,
      "surfaces": [
        {
          "url": "https://news.ycombinator.com/item?id=48954851",
          "name": "Hacker News",
          "points": 594,
          "comments": 62
        },
        {
          "url": "https://lobste.rs/s/ihel7n/regressive_jpegs",
          "name": "Lobsters",
          "points": 76,
          "comments": 2
        },
        {
          "url": "https://maurycyz.com/projects/bad_jpeg/",
          "name": "Hacker News",
          "points": null,
          "comments": null
        },
        {
          "url": "https://maurycyz.com/projects/bad_jpeg/",
          "name": "Lobsters",
          "points": null,
          "comments": null
        },
        {
          "url": "https://programming.dev/post/53707491",
          "name": "programming.dev (Lemmy)",
          "points": null,
          "comments": null
        }
      ],
      "velocity_hours": 0.8,
      "points": 670,
      "comments": 64,
      "score": 14.3,
      "curated": true,
      "pick_id": 215381
    },
    {
      "story_id": "s_c259480fa27c1e19",
      "title": "Learning a few things about running SQLite",
      "canonical_url": "https://jvns.ca/blog/2026/07/17/learning-about-running-sqlite",
      "first_seen": "2026-07-17T00:00:00+00:00",
      "surface_count": 5,
      "surfaces": [
        {
          "url": "https://news.ycombinator.com/item?id=48950122",
          "name": "Hacker News",
          "points": 307,
          "comments": 77
        },
        {
          "url": "https://lobste.rs/s/ryksor/learning_few_things_about_running_sqlite",
          "name": "Lobsters",
          "points": 62,
          "comments": 9
        },
        {
          "url": "https://jvns.ca/blog/2026/07/17/learning-about-running-sqlite/",
          "name": "Julia Evans (jvns.ca)",
          "points": null,
          "comments": null
        },
        {
          "url": "https://jvns.ca/blog/2026/07/17/learning-about-running-sqlite/",
          "name": "Hacker News",
          "points": null,
          "comments": null
        },
        {
          "url": "https://jvns.ca/blog/2026/07/17/learning-about-running-sqlite/",
          "name": "Lobsters",
          "points": null,
          "comments": null
        }
      ],
      "velocity_hours": 0.6,
      "points": 369,
      "comments": 86,
      "score": 14.06,
      "curated": true,
      "pick_id": 168938
    },
    {
      "story_id": "s_1a96e7ae50481b25",
      "title": "Pushing the Primordial Frontier: Cosmological Collider Signatures at Strong Mixing",
      "canonical_url": "https://arxiv.org/abs/2607.14529",
      "first_seen": "2026-07-17T04:00:00+00:00",
      "surface_count": 4,
      "surfaces": [
        {
          "url": "https://arxiv.org/abs/2607.14529",
          "name": "arXiv astro-ph",
          "points": null,
          "comments": null
        },
        {
          "url": "https://arxiv.org/abs/2607.14529",
          "name": "arXiv gr-qc",
          "points": null,
          "comments": null
        },
        {
          "url": "https://arxiv.org/abs/2607.14529",
          "name": "arXiv hep-ph",
          "points": null,
          "comments": null
        },
        {
          "url": "https://arxiv.org/abs/2607.14529",
          "name": "arXiv hep-th",
          "points": null,
          "comments": null
        }
      ],
      "velocity_hours": 0.0,
      "points": 0,
      "comments": 0,
      "score": 10.0,
      "curated": false,
      "pick_id": null
    },
    {
      "story_id": "s_8e3c53c980acc4fe",
      "title": "Scientists built a camera that can track invisible particles in 3D",
      "canonical_url": "https://sciencedaily.com/releases/2026/07/260716023610.htm",
      "first_seen": "2026-07-17T06:04:57+00:00",
      "surface_count": 4,
      "surfaces": [
        {
          "url": "https://www.sciencedaily.com/releases/2026/07/260716023610.htm",
          "name": "ScienceDaily Matter & Energy",
          "points": null,
          "comments": null
        },
        {
          "url": "https://www.sciencedaily.com/releases/2026/07/260716023610.htm",
          "name": "ScienceDaily Technology",
          "points": null,
          "comments": null
        },
        {
          "url": "https://www.sciencedaily.com/releases/2026/07/260716023610.htm",
          "name": "ScienceDaily Top Science",
          "points": null,
          "comments": null
        },
        {
          "url": "https://www.sciencedaily.com/releases/2026/07/260716023610.htm",
          "name": "ScienceDaily Technology",
          "points": null,
          "comments": null
        }
      ],
      "velocity_hours": 0.7,
      "points": 0,
      "comments": 0,
      "score": 10.0,
      "curated": false,
      "pick_id": null
    },
    {
      "story_id": "s_ffbf283b053a48cf",
      "title": "The Growing Crescent of Mars as NASA’s Psyche Mission Approaches",
      "canonical_url": "https://science.nasa.gov/photojournal/the-growing-crescent-of-mars-as-nasas-psyche-mission-approaches",
      "first_seen": "2026-07-17T22:32:27+00:00",
      "surface_count": 4,
      "surfaces": [
        {
          "url": "https://science.nasa.gov/photojournal/the-growing-crescent-of-mars-as-nasas-psyche-mission-approaches/",
          "name": "NASA Breaking News",
          "points": null,
          "comments": null
        },
        {
          "url": "https://science.nasa.gov/photojournal/the-growing-crescent-of-mars-as-nasas-psyche-mission-approaches/",
          "name": "NASA Science News",
          "points": null,
          "comments": null
        },
        {
          "url": "https://science.nasa.gov/photojournal/the-growing-crescent-of-mars-as-nasas-psyche-mission-approaches/",
          "name": "NASA Earth Observatory",
          "points": null,
          "comments": null
        },
        {
          "url": "https://science.nasa.gov/photojournal/the-growing-crescent-of-mars-as-nasas-psyche-mission-approaches/",
          "name": "NASA Breaking News",
          "points": null,
          "comments": null
        }
      ],
      "velocity_hours": 0.0,
      "points": 0,
      "comments": 0,
      "score": 10.0,
      "curated": false,
      "pick_id": null
    },
    {
      "story_id": "s_48b0bf858b8d77ab",
      "title": "NASA’s James Webb catches a supermassive black hole feeding",
      "canonical_url": "https://sciencedaily.com/releases/2026/07/260716023601.htm",
      "first_seen": "2026-07-18T03:09:35+00:00",
      "surface_count": 4,
      "surfaces": [
        {
          "url": "https://www.sciencedaily.com/releases/2026/07/260716023601.htm",
          "name": "ScienceDaily Matter & Energy",
          "points": null,
          "comments": null
        },
        {
          "url": "https://www.sciencedaily.com/releases/2026/07/260716023601.htm",
          "name": "ScienceDaily Technology",
          "points": null,
          "comments": null
        },
        {
          "url": "https://www.sciencedaily.com/releases/2026/07/260716023601.htm",
          "name": "ScienceDaily Top Science",
          "points": null,
          "comments": null
        },
        {
          "url": "https://www.sciencedaily.com/releases/2026/07/260716023601.htm",
          "name": "ScienceDaily Technology",
          "points": null,
          "comments": null
        }
      ],
      "velocity_hours": 0.1,
      "points": 0,
      "comments": 0,
      "score": 10.0,
      "curated": false,
      "pick_id": null
    },
    {
      "story_id": "s_9a324b0fce665571",
      "title": "“Silly sprinklers” help scientists finally solve Feynman’s famous sprinkler mystery",
      "canonical_url": "https://sciencedaily.com/releases/2026/07/260715083535.htm",
      "first_seen": "2026-07-17T13:58:52+00:00",
      "surface_count": 4,
      "surfaces": [
        {
          "url": "https://www.sciencedaily.com/releases/2026/07/260715083535.htm",
          "name": "ScienceDaily Matter & Energy",
          "points": null,
          "comments": null
        },
        {
          "url": "https://www.sciencedaily.com/releases/2026/07/260715083535.htm",
          "name": "ScienceDaily Technology",
          "points": null,
          "comments": null
        },
        {
          "url": "https://www.sciencedaily.com/releases/2026/07/260715083535.htm",
          "name": "ScienceDaily Top Science",
          "points": null,
          "comments": null
        },
        {
          "url": "https://www.sciencedaily.com/releases/2026/07/260715083535.htm",
          "name": "ScienceDaily Technology",
          "points": null,
          "comments": null
        }
      ],
      "velocity_hours": 0.1,
      "points": 0,
      "comments": 0,
      "score": 10.0,
      "curated": false,
      "pick_id": null
    }
  ]
}
